audit_trail_sdk/__init__.py
audit_trail_sdk/client.py
audit_trail_sdk/exceptions.py
audit_trail_sdk/http_client.py
audit_trail_sdk/models.py
audit_trail_sdk/retry.py
audit_trail_sdk/types.py
audit_trail_sdk-1.0.0.dist-info/METADATA
audit_trail_sdk-1.0.0.dist-info/WHEEL
audit_trail_sdk-1.0.0.dist-info/licenses/LICENSE
audit_trail_sdk-1.0.0.dist-info/RECORD
