Metadata-Version: 2.4
Name: audit-trail-sdk
Version: 1.0.0
Summary: Official Python SDK for Audit Trail Universal
Project-URL: Homepage, https://github.com/Mohmk10/audit-trail-server
Project-URL: Documentation, https://github.com/Mohmk10/audit-trail-server#readme
Project-URL: Repository, https://github.com/Mohmk10/audit-trail-server
Author-email: mohmk10 <contact@mohmk10.com>
License-Expression: MIT
License-File: LICENSE
Keywords: audit,compliance,logging,observability,security,trail
Classifier: Development Status :: 4 - Beta
Classifier: Intended Audience :: Developers
Classifier: License :: OSI Approved :: MIT License
Classifier: Programming Language :: Python :: 3
Classifier: Programming Language :: Python :: 3.10
Classifier: Programming Language :: Python :: 3.11
Classifier: Programming Language :: Python :: 3.12
Classifier: Typing :: Typed
Requires-Python: >=3.8
Requires-Dist: httpx>=0.25.0
Requires-Dist: pydantic>=2.5.0
Provides-Extra: dev
Requires-Dist: mypy>=1.7.0; extra == 'dev'
Requires-Dist: pytest-asyncio>=0.21.0; extra == 'dev'
Requires-Dist: pytest-cov>=4.1.0; extra == 'dev'
Requires-Dist: pytest>=7.4.0; extra == 'dev'
Requires-Dist: ruff>=0.1.0; extra == 'dev'
